laundry/__init__.py
laundry/constants.py
laundry/laundry.py
laundry/laundry_cli.py
laundry/laundryclass.py
laundry-2020.2.2.dist-info/LICENSE
laundry-2020.2.2.dist-info/METADATA
laundry-2020.2.2.dist-info/WHEEL
laundry-2020.2.2.dist-info/entry_points.txt
laundry-2020.2.2.dist-info/top_level.txt
laundry-2020.2.2.dist-info/RECORD
