Metadata-Version: 2.1
Name: laundry
Version: 2020.2.2
Summary: Folding spreadsheets into neat shapes.
Home-page: https://github.com/tomackl/laundry
Author: Tom Ackland
Author-email: ackland.thomas@gmail.com
License: UNKNOWN
Platform: UNKNOWN
Classifier: Development Status :: 4 - Beta
Classifier: Operating System :: MacOS :: MacOS X
Classifier: Operating System :: Microsoft :: Windows :: Windows 10
Classifier: License :: OSI Approved :: Apache Software License
Classifier: Programming Language :: Python
Classifier: Programming Language :: Python :: 3.6
Classifier: Programming Language :: Python :: 3.7
Requires-Python: >=3.6
Requires-Dist: Click
Requires-Dist: Pandas
Requires-Dist: python-docx
Requires-Dist: pyjanitor
Requires-Dist: colorama
